{
  "Type": "Choice",
  "Title": "dialogue.username.name",
  "Entries": [
    {
      "Content": "dialogue.IntroDialogue03.content.0",
      "Next": {
        "BlockIdentifier": "IntroDialogue03_C01",
        "Type": "Dialogue",
        "Title": "dialogue.Hans.name",
        "Entries": [
          {
            "Content": "dialogue.IntroDialogue03_C01.content.0"
          }
        ]
      }
    },
    {
      "Content": "dialogue.IntroDialogue03.content.1",
      "NextId": "IntroDialogue03_C02"
    },
    {
      "Content": "dialogue.IntroDialogue03.content.2"
    }
  ]
}
